MANIFEST.in
README.txt
setup.py
MicroPipe/Micro_pipeline.py
MicroPipe/__init__.py
MicroPipe.egg-info/PKG-INFO
MicroPipe.egg-info/SOURCES.txt
MicroPipe.egg-info/dependency_links.txt
MicroPipe.egg-info/requires.txt
MicroPipe.egg-info/top_level.txt
MicroPipe.egg-info/zip-safe
MicroPipe/Config/.general.ini.swp
MicroPipe/Config/__init__.py
MicroPipe/Config/config.ini
MicroPipe/Config/general.ini
MicroPipe/Lib/Dependcy.py
MicroPipe/Lib/__init__.py
MicroPipe/Scripts/Circula.py
MicroPipe/Scripts/Circular_Graph_Draw.py
MicroPipe/Scripts/Download_reference.py
MicroPipe/Scripts/Draw_qc.py
MicroPipe/Scripts/Fasta_split.py
MicroPipe/Scripts/__init__.py
MicroPipe/Scripts/ptt_rnt.py
MicroPipe/Scripts/thu.py