Metadata-Version: 1.1
Name: MicroPipe
Version: 0.2.14
Summary:  A package for automated microbe bioinfomatics Analysis
Home-page: https://github.com/lpp1985/lpp_Script
Author: Pengpeng Li
Author-email: 409511038@qq.com
License: UNKNOWN
Keywords: Pipeline Bioinfomatics
Platform: UNKNOWN
Classifier: Programming Language :: Python
Classifier: Intended Audience :: Developers
Classifier: Operating System :: OS Independent
Classifier: Programming Language :: Python :: 2
